<?xml version="1.0" encoding="utf-8"?>
<ArrayOfStavkaProdajeNamestaja xmlns:xsi="http://www.w3.org/2001/XMLSchema-instance" xmlns:xsd="http://www.w3.org/2001/XMLSchema">
  <StavkaProdajeNamestaja>
    <Id_Racun>1</Id_Racun>
    <Id_Namestaj>1</Id_Namestaj>
    <Kolicina>5</Kolicina>
  </StavkaProdajeNamestaja>
  <StavkaProdajeNamestaja>
    <Id_Racun>1</Id_Racun>
    <Id_Namestaj>9</Id_Namestaj>
    <Kolicina>3</Kolicina>
  </StavkaProdajeNamestaja>
  <StavkaProdajeNamestaja>
    <Id_Racun>2</Id_Racun>
    <Id_Namestaj>1</Id_Namestaj>
    <Kolicina>2</Kolicina>
  </StavkaProdajeNamestaja>
  <StavkaProdajeNamestaja>
    <Id_Racun>2</Id_Racun>
    <Id_Namestaj>9</Id_Namestaj>
    <Kolicina>4</Kolicina>
  </StavkaProdajeNamestaja>
  <StavkaProdajeNamestaja>
    <Id_Racun>2</Id_Racun>
    <Id_Namestaj>6</Id_Namestaj>
    <Kolicina>3</Kolicina>
  </StavkaProdajeNamestaja>
  <StavkaProdajeNamestaja>
    <Id_Racun>3</Id_Racun>
    <Id_Namestaj>5</Id_Namestaj>
    <Kolicina>2</Kolicina>
  </StavkaProdajeNamestaja>
  <StavkaProdajeNamestaja>
    <Id_Racun>3</Id_Racun>
    <Id_Namestaj>4</Id_Namestaj>
    <Kolicina>3</Kolicina>
  </StavkaProdajeNamestaja>
  <StavkaProdajeNamestaja>
    <Id_Racun>4</Id_Racun>
    <Id_Namestaj>9</Id_Namestaj>
    <Kolicina>3</Kolicina>
  </StavkaProdajeNamestaja>
  <StavkaProdajeNamestaja>
    <Id_Racun>4</Id_Racun>
    <Id_Namestaj>5</Id_Namestaj>
    <Kolicina>2</Kolicina>
  </StavkaProdajeNamestaja>
  <StavkaProdajeNamestaja>
    <Id_Racun>5</Id_Racun>
    <Id_Namestaj>1</Id_Namestaj>
    <Kolicina>8</Kolicina>
  </StavkaProdajeNamestaja>
  <StavkaProdajeNamestaja>
    <Id_Racun>5</Id_Racun>
    <Id_Namestaj>8</Id_Namestaj>
    <Kolicina>2</Kolicina>
  </StavkaProdajeNamestaja>
  <StavkaProdajeNamestaja>
    <Id_Racun>6</Id_Racun>
    <Id_Namestaj>1</Id_Namestaj>
    <Kolicina>6</Kolicina>
  </StavkaProdajeNamestaja>
  <StavkaProdajeNamestaja>
    <Id_Racun>6</Id_Racun>
    <Id_Namestaj>10</Id_Namestaj>
    <Kolicina>4</Kolicina>
  </StavkaProdajeNamestaja>
  <StavkaProdajeNamestaja>
    <Id_Racun>7</Id_Racun>
    <Id_Namestaj>1</Id_Namestaj>
    <Kolicina>3</Kolicina>
  </StavkaProdajeNamestaja>
  <StavkaProdajeNamestaja>
    <Id_Racun>8</Id_Racun>
    <Id_Namestaj>1</Id_Namestaj>
    <Kolicina>5</Kolicina>
  </StavkaProdajeNamestaja>
  <StavkaProdajeNamestaja>
    <Id_Racun>8</Id_Racun>
    <Id_Namestaj>9</Id_Namestaj>
    <Kolicina>2</Kolicina>
  </StavkaProdajeNamestaja>
  <StavkaProdajeNamestaja>
    <Id_Racun>9</Id_Racun>
    <Id_Namestaj>10</Id_Namestaj>
    <Kolicina>3</Kolicina>
  </StavkaProdajeNamestaja>
  <StavkaProdajeNamestaja>
    <Id_Racun>10</Id_Racun>
    <Id_Namestaj>1</Id_Namestaj>
    <Kolicina>5</Kolicina>
  </StavkaProdajeNamestaja>
  <StavkaProdajeNamestaja>
    <Id_Racun>11</Id_Racun>
    <Id_Namestaj>10</Id_Namestaj>
    <Kolicina>5</Kolicina>
  </StavkaProdajeNamestaja>
  <StavkaProdajeNamestaja>
    <Id_Racun>11</Id_Racun>
    <Id_Namestaj>9</Id_Namestaj>
    <Kolicina>2</Kolicina>
  </StavkaProdajeNamestaja>
  <StavkaProdajeNamestaja>
    <Id_Racun>12</Id_Racun>
    <Id_Namestaj>9</Id_Namestaj>
    <Kolicina>10</Kolicina>
  </StavkaProdajeNamestaja>
  <StavkaProdajeNamestaja>
    <Id_Racun>13</Id_Racun>
    <Id_Namestaj>1</Id_Namestaj>
    <Kolicina>3</Kolicina>
  </StavkaProdajeNamestaja>
  <StavkaProdajeNamestaja>
    <Id_Racun>14</Id_Racun>
    <Id_Namestaj>10</Id_Namestaj>
    <Kolicina>3</Kolicina>
  </StavkaProdajeNamestaja>
  <StavkaProdajeNamestaja>
    <Id_Racun>15</Id_Racun>
    <Id_Namestaj>1</Id_Namestaj>
    <Kolicina>3</Kolicina>
  </StavkaProdajeNamestaja>
  <StavkaProdajeNamestaja>
    <Id_Racun>16</Id_Racun>
    <Id_Namestaj>1</Id_Namestaj>
    <Kolicina>4</Kolicina>
  </StavkaProdajeNamestaja>
  <StavkaProdajeNamestaja>
    <Id_Racun>17</Id_Racun>
    <Id_Namestaj>10</Id_Namestaj>
    <Kolicina>3</Kolicina>
  </StavkaProdajeNamestaja>
  <StavkaProdajeNamestaja>
    <Id_Racun>17</Id_Racun>
    <Id_Namestaj>8</Id_Namestaj>
    <Kolicina>4</Kolicina>
  </StavkaProdajeNamestaja>
  <StavkaProdajeNamestaja>
    <Id_Racun>18</Id_Racun>
    <Id_Namestaj>10</Id_Namestaj>
    <Kolicina>5</Kolicina>
  </StavkaProdajeNamestaja>
  <StavkaProdajeNamestaja>
    <Id_Racun>18</Id_Racun>
    <Id_Namestaj>9</Id_Namestaj>
    <Kolicina>3</Kolicina>
  </StavkaProdajeNamestaja>
  <StavkaProdajeNamestaja>
    <Id_Racun>19</Id_Racun>
    <Id_Namestaj>1</Id_Namestaj>
    <Kolicina>3</Kolicina>
  </StavkaProdajeNamestaja>
  <StavkaProdajeNamestaja>
    <Id_Racun>19</Id_Racun>
    <Id_Namestaj>9</Id_Namestaj>
    <Kolicina>3</Kolicina>
  </StavkaProdajeNamestaja>
  <StavkaProdajeNamestaja>
    <Id_Racun>20</Id_Racun>
    <Id_Namestaj>1</Id_Namestaj>
    <Kolicina>4</Kolicina>
  </StavkaProdajeNamestaja>
  <StavkaProdajeNamestaja>
    <Id_Racun>20</Id_Racun>
    <Id_Namestaj>10</Id_Namestaj>
    <Kolicina>3</Kolicina>
  </StavkaProdajeNamestaja>
  <StavkaProdajeNamestaja>
    <Id_Racun>21</Id_Racun>
    <Id_Namestaj>5</Id_Namestaj>
    <Kolicina>5</Kolicina>
  </StavkaProdajeNamestaja>
  <StavkaProdajeNamestaja>
    <Id_Racun>21</Id_Racun>
    <Id_Namestaj>1</Id_Namestaj>
    <Kolicina>1</Kolicina>
  </StavkaProdajeNamestaja>
  <StavkaProdajeNamestaja>
    <Id_Racun>22</Id_Racun>
    <Id_Namestaj>3</Id_Namestaj>
    <Kolicina>5</Kolicina>
  </StavkaProdajeNamestaja>
</ArrayOfStavkaProdajeNamestaja>